tensorrt_yolo/__init__.py
tensorrt_yolo/cli.py
tensorrt_yolo/export/__init__.py
tensorrt_yolo/export/head.py
tensorrt_yolo/export/ppyoloe.py
tensorrt_yolo_copy/__init__.py
tensorrt_yolo_copy/c_lib_wrap.py
tensorrt_yolo_copy/cli.py
tensorrt_yolo_copy/export/__init__.py
tensorrt_yolo_copy/export/head.py
tensorrt_yolo_copy/export/ppyoloe.py
tensorrt_yolo_copy/infer/__init__.py
tensorrt_yolo_copy/infer/detection.py
tensorrt_yolo_copy/infer/result.py
tensorrt_yolo_copy/infer/timer.py
tensorrt_yolo_copy/infer/visualize.py
tensorrt_yolo_copy/libs/__init__.py
tensorrt_yolo-4.3.1.dist-info/LICENSE
tensorrt_yolo-4.3.1.dist-info/METADATA
tensorrt_yolo-4.3.1.dist-info/WHEEL
tensorrt_yolo-4.3.1.dist-info/entry_points.txt
tensorrt_yolo-4.3.1.dist-info/top_level.txt
tensorrt_yolo-4.3.1.dist-info/RECORD
